consolemd/__init__.py
consolemd/cli.py
consolemd/colormap.py
consolemd/escapeseq.py
consolemd/logger.py
consolemd/renderer.py
consolemd/styler.py
consolemd-0.5.1.dist-info/LICENSE.md
consolemd-0.5.1.dist-info/METADATA
consolemd-0.5.1.dist-info/WHEEL
consolemd-0.5.1.dist-info/entry_points.txt
consolemd-0.5.1.dist-info/pbr.json
consolemd-0.5.1.dist-info/top_level.txt
consolemd-0.5.1.dist-info/RECORD
